llm_easy_tools/__init__.py
llm_easy_tools/processor.py
llm_easy_tools/schema_generator.py
llm_easy_tools/types.py
LLMEasyTools-0.25.dist-info/LICENSE
LLMEasyTools-0.25.dist-info/METADATA
LLMEasyTools-0.25.dist-info/WHEEL
LLMEasyTools-0.25.dist-info/top_level.txt
LLMEasyTools-0.25.dist-info/RECORD
