Metadata-Version: 2.1
Name: LLMEasyTools
Version: 0.25
Summary: Tools for LLM agents.
Author: Natalia Borovskikh
Author-email: Zbigniew Łukasiak <zzbbyy@gmail.com>
License: Apache License
Project-URL: repository, https://github.com/zby/LLMEasyTools
Classifier: Development Status :: 3 - Alpha
Classifier: Intended Audience :: Developers
Classifier: Topic :: Software Development :: Libraries :: Python Modules
Classifier: License :: OSI Approved :: Apache Software License
Classifier: Programming Language :: Python
Classifier: Programming Language :: Python :: 3
Classifier: Operating System :: OS Independent
License-File: LICENSE
Requires-Dist: pydantic
Requires-Dist: docstring-parser~=0.15
Provides-Extra: examples
Requires-Dist: openai; extra == "examples"
Provides-Extra: test
Requires-Dist: pytest~=7.4.4; extra == "test"
